super_cool_printer_test/__init__.py
super_cool_printer_test/add.py
super_cool_printer_test/subtract.py
super_cool_printer_test/extras/__init__.py
super_cool_printer_test/extras/divide.py
super_cool_printer_test/extras/multiply.py
test_super_cool_printer/__init__.py
test_super_cool_printer/add.py
test_super_cool_printer/subtract.py
test_super_cool_printer/extras/__init__.py
test_super_cool_printer/extras/divide.py
test_super_cool_printer/extras/multiply.py
verysimplemodule/__init__.py
verysimplemodule/add.py
verysimplemodule/subtract.py
verysimplemodule/extras/__init__.py
verysimplemodule/extras/divide.py
verysimplemodule/extras/multiply.py
super_cool_printer_test-0.0.1.dist-info/METADATA
super_cool_printer_test-0.0.1.dist-info/WHEEL
super_cool_printer_test-0.0.1.dist-info/top_level.txt
super_cool_printer_test-0.0.1.dist-info/RECORD
